auto_deprecator/__init__.py
auto_deprecator-2020.5.0.dist-info/LICENSE
auto_deprecator-2020.5.0.dist-info/METADATA
auto_deprecator-2020.5.0.dist-info/WHEEL
auto_deprecator-2020.5.0.dist-info/entry_points.txt
auto_deprecator-2020.5.0.dist-info/top_level.txt
auto_deprecator-2020.5.0.dist-info/RECORD
