Metadata-Version: 2.1
Name: auto-deprecator
Version: 2020.5.0
Summary: Python decorator and command to automate deprecating components
Home-page: https://github.com/auto-deprecator/auto-deprecator
Author: Gavin Chan
Author-email: gavincyi@gmail.com
License: MIT license
Keywords: auto_deprecator
Platform: UNKNOWN
Classifier: Development Status :: 2 - Pre-Alpha
Classifier: Intended Audience :: Developers
Classifier: License :: OSI Approved :: MIT License
Classifier: Natural Language :: English
Classifier: Programming Language :: Python :: 3
Classifier: Programming Language :: Python :: 3.5
Classifier: Programming Language :: Python :: 3.6
Classifier: Programming Language :: Python :: 3.7
Classifier: Programming Language :: Python :: 3.8
Requires-Python: >=3.5
Provides-Extra: test
Requires-Dist: pytest (>=3) ; extra == 'test'
